{"cameraMode":{"drawMode":0,"name":"Shaded","section":"Shading Mode"},"sceneLighting":true,"audioPlay":false,"sceneViewState":{"showFog":true,"showMaterialUpdate":false,"showSkybox":true,"showFlares":true,"showImageEffects":true,"showParticleSystems":true},"in2DMode":false,"pivot":{"x":2.4797682762145998,"y":0.16957569122314454,"z":4.482131481170654},"rotation":{"x":-0.39276042580604555,"y":0.026751870289444925,"z":-0.011433633975684643,"w":-0.9191867709159851},"size":11.6919527053833,"orthographic":false}